sqladbx/__init__.py
sqladbx/context.py
sqladbx/exceptions.py
sqladbx/middleware.py
sqladbx/proxy.py
sqladbx/py.typed
sqladbx/session.py
sqladbx-0.0.4.dist-info/METADATA
sqladbx-0.0.4.dist-info/WHEEL
sqladbx-0.0.4.dist-info/RECORD
