Metadata-Version: 2.4
Name: sqladbx
Version: 0.0.4
Summary: Modern async SQLAlchemy database context manager for FastAPI, Taskiq, Temporal, and more
Project-URL: homepage, https://github.com/swaldom/sqladbx
Project-URL: repository, https://github.com/swaldom/sqladbx
Project-URL: documentation, https://github.com/swaldom/sqladbx#readme
Project-URL: issues, https://github.com/swaldom/sqladbx/issues
Author-email: Oleksii Svichkar <oswops@gmail.com>
License: MIT
Keywords: async,context,db,fastapi,middleware,sqlalchemy,temporal
Classifier: Development Status :: 4 - Beta
Classifier: Environment :: Web Environment
Classifier: Framework :: AsyncIO
Classifier: Intended Audience :: Developers
Classifier: License :: OSI Approved :: MIT License
Classifier: Operating System :: OS Independent
Classifier: Programming Language :: Python :: 3 :: Only
Classifier: Programming Language :: Python :: 3.13
Classifier: Programming Language :: Python :: 3.14
Classifier: Programming Language :: Python :: Implementation :: CPython
Classifier: Topic :: Internet :: WWW/HTTP :: Dynamic Content
Classifier: Topic :: Software Development :: Libraries :: Python Modules
Requires-Python: >=3.13
Requires-Dist: sqlalchemy>=2.0
Requires-Dist: starlette>=0.13.6
Provides-Extra: build
Requires-Dist: hatch>=1.16.2; extra == 'build'
Provides-Extra: examples
Requires-Dist: fastapi-cli>=0.0.16; extra == 'examples'
Requires-Dist: loguru>=0.7.3; extra == 'examples'
Requires-Dist: redis>=7.0.1; extra == 'examples'
Requires-Dist: taskiq-redis>=1.2.0; extra == 'examples'
Provides-Extra: test
Requires-Dist: aiosqlite>=0.22.0; extra == 'test'
Requires-Dist: fastapi>=0.124.4; extra == 'test'
Requires-Dist: greenlet>=3.3.0; extra == 'test'
Requires-Dist: httpx>=0.28.1; extra == 'test'
Requires-Dist: litestar>=2.19.0; extra == 'test'
Requires-Dist: pytest-asyncio>=0.21; extra == 'test'
Requires-Dist: pytest-cov>=4.0; extra == 'test'
Requires-Dist: pytest>=9.0.2; extra == 'test'
Requires-Dist: sqlmodel>=0.0.27; extra == 'test'
Requires-Dist: taskiq>=0.12.1; extra == 'test'
Requires-Dist: temporalio>=1.20.0; extra == 'test'
